<?xml version="1.0" encoding="UTF-8"?>
<export version="E">
  <design>
    <source>C:\Users\penta\Documents\BikeRadar\RFB\BajieHeader\BajieHeader.kicad_sch</source>
    <date>2023-05-26 01:00:08</date>
    <tool>Eeschema (6.0.4)</tool>
    <sheet number="1" name="/" tstamps="/">
      <title_block>
        <title/>
        <company/>
        <rev/>
        <date/>
        <source>BajieHeader.kicad_sch</source>
        <comment number="1" value=""/>
        <comment number="2" value=""/>
        <comment number="3" value=""/>
        <comment number="4" value=""/>
        <comment number="5" value=""/>
        <comment number="6" value=""/>
        <comment number="7" value=""/>
        <comment number="8" value=""/>
        <comment number="9" value=""/>
      </title_block>
    </sheet>
  </design>
  <components>
    <comp ref="C1">
      <value>100n</value>
      <footprint>Capacitor_SMD:C_0402_1005Metric</footprint>
      <libsource lib="Device" part="C_Small" description="Unpolarized capacitor, small symbol"/>
      <property name="Sheetname" value=""/>
      <property name="Sheetfile" value="BajieHeader.kicad_sch"/>
      <sheetpath names="/" tstamps="/"/>
      <tstamps>d67d64d1-f719-4019-bb39-a9f810b00e60</tstamps>
    </comp>
    <comp ref="C2">
      <value>10u</value>
      <footprint>Capacitor_SMD:C_0603_1608Metric</footprint>
      <libsource lib="Device" part="C_Small" description="Unpolarized capacitor, small symbol"/>
      <property name="Sheetname" value=""/>
      <property name="Sheetfile" value="BajieHeader.kicad_sch"/>
      <sheetpath names="/" tstamps="/"/>
      <tstamps>de1fb855-a648-488c-9fc8-c2e7c48ed7d6</tstamps>
    </comp>
    <comp ref="C3">
      <value>2u2</value>
      <footprint>Capacitor_SMD:C_0603_1608Metric</footprint>
      <libsource lib="Device" part="C_Small" description="Unpolarized capacitor, small symbol"/>
      <property name="Sheetname" value=""/>
      <property name="Sheetfile" value="BajieHeader.kicad_sch"/>
      <sheetpath names="/" tstamps="/"/>
      <tstamps>7a289eba-f626-41bf-8419-f5e4380e1684</tstamps>
    </comp>
    <comp ref="C4">
      <value>2u2</value>
      <footprint>Capacitor_SMD:C_0603_1608Metric</footprint>
      <libsource lib="Device" part="C_Small" description="Unpolarized capacitor, small symbol"/>
      <property name="Sheetname" value=""/>
      <property name="Sheetfile" value="BajieHeader.kicad_sch"/>
      <sheetpath names="/" tstamps="/"/>
      <tstamps>0006ad43-2e29-466c-87de-e10ea4c5d6ef</tstamps>
    </comp>
    <comp ref="C5">
      <value>2u2</value>
      <footprint>Capacitor_SMD:C_0603_1608Metric</footprint>
      <libsource lib="Device" part="C_Small" description="Unpolarized capacitor, small symbol"/>
      <property name="Sheetname" value=""/>
      <property name="Sheetfile" value="BajieHeader.kicad_sch"/>
      <sheetpath names="/" tstamps="/"/>
      <tstamps>cbc230c0-e2ba-407e-9d0a-c7092d01a95b</tstamps>
    </comp>
    <comp ref="C6">
      <value>100n</value>
      <footprint>Capacitor_SMD:C_0402_1005Metric</footprint>
      <libsource lib="Device" part="C_Small" description="Unpolarized capacitor, small symbol"/>
      <property name="Sheetname" value=""/>
      <property name="Sheetfile" value="BajieHeader.kicad_sch"/>
      <sheetpath names="/" tstamps="/"/>
      <tstamps>23a9e4f6-bab7-4875-92a9-590c9d7f850b</tstamps>
    </comp>
    <comp ref="C7">
      <value>100n</value>
      <footprint>Capacitor_SMD:C_0402_1005Metric</footprint>
      <libsource lib="Device" part="C_Small" description="Unpolarized capacitor, small symbol"/>
      <property name="Sheetname" value=""/>
      <property name="Sheetfile" value="BajieHeader.kicad_sch"/>
      <sheetpath names="/" tstamps="/"/>
      <tstamps>c3952324-dc1e-43f3-8abe-7261fb17e314</tstamps>
    </comp>
    <comp ref="C8">
      <value>100n</value>
      <footprint>Capacitor_SMD:C_0402_1005Metric</footprint>
      <libsource lib="Device" part="C_Small" description="Unpolarized capacitor, small symbol"/>
      <property name="Sheetname" value=""/>
      <property name="Sheetfile" value="BajieHeader.kicad_sch"/>
      <sheetpath names="/" tstamps="/"/>
      <tstamps>b44d1ec2-a910-48c7-9bd2-9bd3d1ac7883</tstamps>
    </comp>
    <comp ref="C9">
      <value>10u</value>
      <footprint>Capacitor_SMD:C_0603_1608Metric</footprint>
      <libsource lib="Device" part="C_Small" description="Unpolarized capacitor, small symbol"/>
      <property name="Sheetname" value=""/>
      <property name="Sheetfile" value="BajieHeader.kicad_sch"/>
      <sheetpath names="/" tstamps="/"/>
      <tstamps>62bf82f0-f187-4349-9070-66205804ab7c</tstamps>
    </comp>
    <comp ref="C10">
      <value>10u</value>
      <footprint>Capacitor_SMD:C_0603_1608Metric</footprint>
      <libsource lib="Device" part="C_Small" description="Unpolarized capacitor, small symbol"/>
      <property name="Sheetname" value=""/>
      <property name="Sheetfile" value="BajieHeader.kicad_sch"/>
      <sheetpath names="/" tstamps="/"/>
      <tstamps>d22a72f3-81b4-4d0a-8627-919cd7323de5</tstamps>
    </comp>
    <comp ref="C11">
      <value>10u</value>
      <footprint>Capacitor_SMD:C_0603_1608Metric</footprint>
      <libsource lib="Device" part="C_Small" description="Unpolarized capacitor, small symbol"/>
      <property name="Sheetname" value=""/>
      <property name="Sheetfile" value="BajieHeader.kicad_sch"/>
      <sheetpath names="/" tstamps="/"/>
      <tstamps>6d03afc0-9b59-4fd0-b6f9-d1fe96eb7fb3</tstamps>
    </comp>
    <comp ref="C12">
      <value>10u</value>
      <footprint>Capacitor_SMD:C_0603_1608Metric</footprint>
      <libsource lib="Device" part="C_Small" description="Unpolarized capacitor, small symbol"/>
      <property name="Sheetname" value=""/>
      <property name="Sheetfile" value="BajieHeader.kicad_sch"/>
      <sheetpath names="/" tstamps="/"/>
      <tstamps>f5c4d9e1-a44f-4803-be5b-2b6aac3c3859</tstamps>
    </comp>
    <comp ref="C13">
      <value>100n</value>
      <footprint>Capacitor_SMD:C_0402_1005Metric</footprint>
      <libsource lib="Device" part="C_Small" description="Unpolarized capacitor, small symbol"/>
      <property name="Sheetname" value=""/>
      <property name="Sheetfile" value="BajieHeader.kicad_sch"/>
      <sheetpath names="/" tstamps="/"/>
      <tstamps>dd832f1f-0ab4-4f77-9d06-284139ffa703</tstamps>
    </comp>
    <comp ref="C14">
      <value>100n</value>
      <footprint>Capacitor_SMD:C_0402_1005Metric</footprint>
      <libsource lib="Device" part="C_Small" description="Unpolarized capacitor, small symbol"/>
      <property name="Sheetname" value=""/>
      <property name="Sheetfile" value="BajieHeader.kicad_sch"/>
      <sheetpath names="/" tstamps="/"/>
      <tstamps>aae7cab7-614e-4137-9610-5809fd90fac1</tstamps>
    </comp>
    <comp ref="C15">
      <value>100n</value>
      <footprint>Capacitor_SMD:C_0402_1005Metric</footprint>
      <libsource lib="Device" part="C_Small" description="Unpolarized capacitor, small symbol"/>
      <property name="Sheetname" value=""/>
      <property name="Sheetfile" value="BajieHeader.kicad_sch"/>
      <sheetpath names="/" tstamps="/"/>
      <tstamps>72263aa2-32c4-4252-a768-30b77365cca2</tstamps>
    </comp>
    <comp ref="C16">
      <value>10u</value>
      <footprint>Capacitor_SMD:C_0603_1608Metric</footprint>
      <libsource lib="Device" part="C_Small" description="Unpolarized capacitor, small symbol"/>
      <property name="Sheetname" value=""/>
      <property name="Sheetfile" value="BajieHeader.kicad_sch"/>
      <sheetpath names="/" tstamps="/"/>
      <tstamps>76004765-6e34-42e5-bef2-e8d5daedc3a7</tstamps>
    </comp>
    <comp ref="C17">
      <value>10u</value>
      <footprint>Capacitor_SMD:C_0603_1608Metric</footprint>
      <libsource lib="Device" part="C_Small" description="Unpolarized capacitor, small symbol"/>
      <property name="Sheetname" value=""/>
      <property name="Sheetfile" value="BajieHeader.kicad_sch"/>
      <sheetpath names="/" tstamps="/"/>
      <tstamps>0a2fc805-5bca-434a-b0c2-d0d22d640cec</tstamps>
    </comp>
    <comp ref="F1">
      <value>0.2A</value>
      <footprint>Fuse:Fuse_1206_3216Metric</footprint>
      <datasheet>https://www.mouser.com/datasheet/2/447/SMD1206_1-1954982.pdf</datasheet>
      <libsource lib="Device" part="Polyfuse" description="Resettable fuse, polymeric positive temperature coefficient"/>
      <property name="Sheetname" value=""/>
      <property name="Sheetfile" value="BajieHeader.kicad_sch"/>
      <sheetpath names="/" tstamps="/"/>
      <tstamps>abe27209-eb77-491d-92ac-6471cac6cc01</tstamps>
    </comp>
    <comp ref="H1">
      <value>MountingHole_Pad</value>
      <footprint>MountingHole:MountingHole_2.2mm_M2_ISO7380_Pad_TopBottom</footprint>
      <libsource lib="Mechanical" part="MountingHole_Pad" description="Mounting Hole with connection"/>
      <property name="Sheetname" value=""/>
      <property name="Sheetfile" value="BajieHeader.kicad_sch"/>
      <sheetpath names="/" tstamps="/"/>
      <tstamps>21fbbbae-af78-4043-a918-7dd28101b960</tstamps>
    </comp>
    <comp ref="H2">
      <value>MountingHole_Pad</value>
      <footprint>MountingHole:MountingHole_2.2mm_M2_ISO7380_Pad_TopBottom</footprint>
      <libsource lib="Mechanical" part="MountingHole_Pad" description="Mounting Hole with connection"/>
      <property name="Sheetname" value=""/>
      <property name="Sheetfile" value="BajieHeader.kicad_sch"/>
      <sheetpath names="/" tstamps="/"/>
      <tstamps>73c3726f-fffa-493b-b9ef-a876c3b3fcf5</tstamps>
    </comp>
    <comp ref="J1">
      <value>Conn_02x25_Odd_Even</value>
      <footprint>Connector_PinHeader_2.54mm:PinHeader_2x25_P2.54mm_Vertical</footprint>
      <libsource lib="Connector_Generic" part="Conn_02x25_Odd_Even" description="Generic connector, double row, 02x25, odd/even pin numbering scheme (row 1 odd numbers, row 2 even numbers), script generated (kicad-library-utils/schlib/autogen/connector/)"/>
      <property name="Sheetname" value=""/>
      <property name="Sheetfile" value="BajieHeader.kicad_sch"/>
      <sheetpath names="/" tstamps="/"/>
      <tstamps>382e324d-e315-47c6-a284-0bba5b308fd4</tstamps>
    </comp>
    <comp ref="J2">
      <value>Conn_01x16_MountingPin</value>
      <footprint>Connector_FFC-FPC:TE_1-1734839-6_1x16-1MP_P0.5mm_Horizontal</footprint>
      <libsource lib="Connector_Generic_MountingPin" part="Conn_01x16_MountingPin" description="Generic connectable mounting pin connector, single row, 01x16, script generated (kicad-library-utils/schlib/autogen/connector/)"/>
      <property name="Sheetname" value=""/>
      <property name="Sheetfile" value="BajieHeader.kicad_sch"/>
      <sheetpath names="/" tstamps="/"/>
      <tstamps>0aad9c72-116f-49c3-b927-5d61adada2ef</tstamps>
    </comp>
    <comp ref="J3">
      <value>Conn_02x06_Odd_Even</value>
      <footprint>Connector_PinHeader_2.54mm:PinHeader_2x06_P2.54mm_Vertical</footprint>
      <libsource lib="Connector_Generic" part="Conn_02x06_Odd_Even" description="Generic connector, double row, 02x06, odd/even pin numbering scheme (row 1 odd numbers, row 2 even numbers), script generated (kicad-library-utils/schlib/autogen/connector/)"/>
      <property name="Sheetname" value=""/>
      <property name="Sheetfile" value="BajieHeader.kicad_sch"/>
      <sheetpath names="/" tstamps="/"/>
      <tstamps>ad51a56a-f0c9-4e11-8660-1cd25792e8d0</tstamps>
    </comp>
    <comp ref="J4">
      <value>Conn_01x02_Male</value>
      <footprint>Connector_PinHeader_2.54mm:PinHeader_1x02_P2.54mm_Vertical</footprint>
      <libsource lib="Connector" part="Conn_01x02_Male" description="Generic connector, single row, 01x02, script generated (kicad-library-utils/schlib/autogen/connector/)"/>
      <property name="Sheetname" value=""/>
      <property name="Sheetfile" value="BajieHeader.kicad_sch"/>
      <sheetpath names="/" tstamps="/"/>
      <tstamps>8a7103de-1f50-46b7-87f8-e17155c76bd2</tstamps>
    </comp>
    <comp ref="J5">
      <value>Conn_01x02_Male</value>
      <footprint>Connector_PinHeader_2.54mm:PinHeader_1x02_P2.54mm_Vertical</footprint>
      <libsource lib="Connector" part="Conn_01x02_Male" description="Generic connector, single row, 01x02, script generated (kicad-library-utils/schlib/autogen/connector/)"/>
      <property name="Sheetname" value=""/>
      <property name="Sheetfile" value="BajieHeader.kicad_sch"/>
      <sheetpath names="/" tstamps="/"/>
      <tstamps>683d61a1-3404-4aa1-8a68-7d93e898f533</tstamps>
    </comp>
    <comp ref="J6">
      <value>Conn_01x04</value>
      <footprint>Connector_PinHeader_1.27mm:PinHeader_1x04_P1.27mm_Vertical</footprint>
      <libsource lib="Connector_Generic" part="Conn_01x04" description="Generic connector, single row, 01x04, script generated (kicad-library-utils/schlib/autogen/connector/)"/>
      <property name="Sheetname" value=""/>
      <property name="Sheetfile" value="BajieHeader.kicad_sch"/>
      <sheetpath names="/" tstamps="/"/>
      <tstamps>b7198d7b-2279-454c-b70c-6b54db4d7c5c</tstamps>
    </comp>
    <comp ref="J7">
      <value>Conn_01x03_Male</value>
      <footprint>Connector_PinHeader_2.54mm:PinHeader_1x03_P2.54mm_Vertical</footprint>
      <libsource lib="Connector" part="Conn_01x03_Male" description="Generic connector, single row, 01x03, script generated (kicad-library-utils/schlib/autogen/connector/)"/>
      <property name="Sheetname" value=""/>
      <property name="Sheetfile" value="BajieHeader.kicad_sch"/>
      <sheetpath names="/" tstamps="/"/>
      <tstamps>d894b999-55c2-4c8d-9046-68bfe6757c42</tstamps>
    </comp>
    <comp ref="L1">
      <value>3u3</value>
      <footprint>SRP3212A:SRP3212A</footprint>
      <libsource lib="Device" part="L" description="Inductor"/>
      <property name="Sheetname" value=""/>
      <property name="Sheetfile" value="BajieHeader.kicad_sch"/>
      <sheetpath names="/" tstamps="/"/>
      <tstamps>8a1fb092-ba36-4e46-afea-e0ae942b690d</tstamps>
    </comp>
    <comp ref="L2">
      <value>3u3</value>
      <footprint>SRP3212A:SRP3212A</footprint>
      <libsource lib="Device" part="L" description="Inductor"/>
      <property name="Sheetname" value=""/>
      <property name="Sheetfile" value="BajieHeader.kicad_sch"/>
      <sheetpath names="/" tstamps="/"/>
      <tstamps>e59e4bf1-19bd-4e9d-a38d-9c0f723d6ac1</tstamps>
    </comp>
    <comp ref="L3">
      <value>3u3</value>
      <footprint>SRP3212A:SRP3212A</footprint>
      <libsource lib="Device" part="L" description="Inductor"/>
      <property name="Sheetname" value=""/>
      <property name="Sheetfile" value="BajieHeader.kicad_sch"/>
      <sheetpath names="/" tstamps="/"/>
      <tstamps>72eb8031-447e-41e3-aaa5-59f792bf0a9e</tstamps>
    </comp>
    <comp ref="R1">
      <value>100k 1%</value>
      <footprint>Resistor_SMD:R_0402_1005Metric</footprint>
      <libsource lib="Device" part="R_Small" description="Resistor, small symbol"/>
      <property name="Sheetname" value=""/>
      <property name="Sheetfile" value="BajieHeader.kicad_sch"/>
      <sheetpath names="/" tstamps="/"/>
      <tstamps>75a04c79-ef90-4137-bb99-b1909603f570</tstamps>
    </comp>
    <comp ref="R2">
      <value>13k7 1%</value>
      <footprint>Resistor_SMD:R_0402_1005Metric</footprint>
      <libsource lib="Device" part="R_Small" description="Resistor, small symbol"/>
      <property name="Sheetname" value=""/>
      <property name="Sheetfile" value="BajieHeader.kicad_sch"/>
      <sheetpath names="/" tstamps="/"/>
      <tstamps>f2fb0366-6e98-4199-8591-c099fae4402d</tstamps>
    </comp>
    <comp ref="R3">
      <value>100k 1%</value>
      <footprint>Resistor_SMD:R_0402_1005Metric</footprint>
      <libsource lib="Device" part="R_Small" description="Resistor, small symbol"/>
      <property name="Sheetname" value=""/>
      <property name="Sheetfile" value="BajieHeader.kicad_sch"/>
      <sheetpath names="/" tstamps="/"/>
      <tstamps>5a73997b-15c6-4ba6-8b5f-6453a9915589</tstamps>
    </comp>
    <comp ref="R4">
      <value>18k7 1%</value>
      <footprint>Resistor_SMD:R_0402_1005Metric</footprint>
      <libsource lib="Device" part="R_Small" description="Resistor, small symbol"/>
      <property name="Sheetname" value=""/>
      <property name="Sheetfile" value="BajieHeader.kicad_sch"/>
      <sheetpath names="/" tstamps="/"/>
      <tstamps>f2717abd-1a79-4737-9516-231c0b15ad12</tstamps>
    </comp>
    <comp ref="R5">
      <value>100k 1%</value>
      <footprint>Resistor_SMD:R_0402_1005Metric</footprint>
      <libsource lib="Device" part="R_Small" description="Resistor, small symbol"/>
      <property name="Sheetname" value=""/>
      <property name="Sheetfile" value="BajieHeader.kicad_sch"/>
      <sheetpath names="/" tstamps="/"/>
      <tstamps>8d859ebf-9390-4cb5-961d-e7beaa0a4ae4</tstamps>
    </comp>
    <comp ref="R6">
      <value>10k 1%</value>
      <footprint>Resistor_SMD:R_0402_1005Metric</footprint>
      <libsource lib="Device" part="R_Small" description="Resistor, small symbol"/>
      <property name="Sheetname" value=""/>
      <property name="Sheetfile" value="BajieHeader.kicad_sch"/>
      <sheetpath names="/" tstamps="/"/>
      <tstamps>abea12a4-22aa-493e-b609-93e74c746b7c</tstamps>
    </comp>
    <comp ref="U1">
      <value>LMR51430</value>
      <footprint>Package_TO_SOT_SMD:SOT-23-6</footprint>
      <datasheet>https://www.ti.com/lit/ds/symlink/lmr51430.pdf?ts=1684716438866&amp;ref_url=https%253A%252F%252Fwww.ti.com%252Fproduct%252FLMR51430</datasheet>
      <libsource lib="LMR51430" part="LMR51430" description=""/>
      <property name="Sheetname" value=""/>
      <property name="Sheetfile" value="BajieHeader.kicad_sch"/>
      <sheetpath names="/" tstamps="/"/>
      <tstamps>8d2a971f-6107-40d8-9b75-8468cc151feb</tstamps>
    </comp>
    <comp ref="U2">
      <value>LMR51430</value>
      <footprint>Package_TO_SOT_SMD:SOT-23-6</footprint>
      <datasheet>https://www.ti.com/lit/ds/symlink/lmr51430.pdf?ts=1684716438866&amp;ref_url=https%253A%252F%252Fwww.ti.com%252Fproduct%252FLMR51430</datasheet>
      <libsource lib="LMR51430" part="LMR51430" description=""/>
      <property name="Sheetname" value=""/>
      <property name="Sheetfile" value="BajieHeader.kicad_sch"/>
      <sheetpath names="/" tstamps="/"/>
      <tstamps>905d0931-5d67-456d-8e33-3f8ab9a75d07</tstamps>
    </comp>
    <comp ref="U3">
      <value>ISO1044UB</value>
      <footprint>Package_SO:SOIC-8_3.9x4.9mm_P1.27mm</footprint>
      <datasheet>http://www.ti.com/lit/ds/symlink/iso1050.pdf</datasheet>
      <libsource lib="Interface_CAN_LIN" part="ISO1044UB" description="Isolated CAN Transceiver, SOP-8"/>
      <property name="Sheetname" value=""/>
      <property name="Sheetfile" value="BajieHeader.kicad_sch"/>
      <sheetpath names="/" tstamps="/"/>
      <tstamps>eb828bfa-f37b-4838-a8dd-4fc0d4a13f32</tstamps>
    </comp>
    <comp ref="U4">
      <value>LMR51430</value>
      <footprint>Package_TO_SOT_SMD:SOT-23-6</footprint>
      <datasheet>https://www.ti.com/lit/ds/symlink/lmr51430.pdf?ts=1684716438866&amp;ref_url=https%253A%252F%252Fwww.ti.com%252Fproduct%252FLMR51430</datasheet>
      <libsource lib="LMR51430" part="LMR51430" description=""/>
      <property name="Sheetname" value=""/>
      <property name="Sheetfile" value="BajieHeader.kicad_sch"/>
      <sheetpath names="/" tstamps="/"/>
      <tstamps>1ecc1846-9d45-47c8-a9a5-7ee29d34b71f</tstamps>
    </comp>
  </components>
  <libparts>
    <libpart lib="Connector" part="Conn_01x02_Male">
      <description>Generic connector, single row, 01x02, script generated (kicad-library-utils/schlib/autogen/connector/)</description>
      <docs>~</docs>
      <footprints>
        <fp>Connector*:*_1x??_*</fp>
      </footprints>
      <fields>
        <field name="Reference">J</field>
        <field name="Value">Conn_01x02_Male</field>
        <field name="Datasheet">~</field>
      </fields>
      <pins>
        <pin num="1" name="Pin_1" type="passive"/>
        <pin num="2" name="Pin_2" type="passive"/>
      </pins>
    </libpart>
    <libpart lib="Connector" part="Conn_01x03_Male">
      <description>Generic connector, single row, 01x03, script generated (kicad-library-utils/schlib/autogen/connector/)</description>
      <docs>~</docs>
      <footprints>
        <fp>Connector*:*_1x??_*</fp>
      </footprints>
      <fields>
        <field name="Reference">J</field>
        <field name="Value">Conn_01x03_Male</field>
        <field name="Datasheet">~</field>
      </fields>
      <pins>
        <pin num="1" name="Pin_1" type="passive"/>
        <pin num="2" name="Pin_2" type="passive"/>
        <pin num="3" name="Pin_3" type="passive"/>
      </pins>
    </libpart>
    <libpart lib="Connector_Generic" part="Conn_01x04">
      <description>Generic connector, single row, 01x04, script generated (kicad-library-utils/schlib/autogen/connector/)</description>
      <docs>~</docs>
      <footprints>
        <fp>Connector*:*_1x??_*</fp>
      </footprints>
      <fields>
        <field name="Reference">J</field>
        <field name="Value">Conn_01x04</field>
        <field name="Datasheet">~</field>
      </fields>
      <pins>
        <pin num="1" name="Pin_1" type="passive"/>
        <pin num="2" name="Pin_2" type="passive"/>
        <pin num="3" name="Pin_3" type="passive"/>
        <pin num="4" name="Pin_4" type="passive"/>
      </pins>
    </libpart>
    <libpart lib="Connector_Generic" part="Conn_02x06_Odd_Even">
      <description>Generic connector, double row, 02x06, odd/even pin numbering scheme (row 1 odd numbers, row 2 even numbers), script generated (kicad-library-utils/schlib/autogen/connector/)</description>
      <docs>~</docs>
      <footprints>
        <fp>Connector*:*_2x??_*</fp>
      </footprints>
      <fields>
        <field name="Reference">J</field>
        <field name="Value">Conn_02x06_Odd_Even</field>
        <field name="Datasheet">~</field>
      </fields>
      <pins>
        <pin num="1" name="Pin_1" type="passive"/>
        <pin num="2" name="Pin_2" type="passive"/>
        <pin num="3" name="Pin_3" type="passive"/>
        <pin num="4" name="Pin_4" type="passive"/>
        <pin num="5" name="Pin_5" type="passive"/>
        <pin num="6" name="Pin_6" type="passive"/>
        <pin num="7" name="Pin_7" type="passive"/>
        <pin num="8" name="Pin_8" type="passive"/>
        <pin num="9" name="Pin_9" type="passive"/>
        <pin num="10" name="Pin_10" type="passive"/>
        <pin num="11" name="Pin_11" type="passive"/>
        <pin num="12" name="Pin_12" type="passive"/>
      </pins>
    </libpart>
    <libpart lib="Connector_Generic" part="Conn_02x25_Odd_Even">
      <description>Generic connector, double row, 02x25, odd/even pin numbering scheme (row 1 odd numbers, row 2 even numbers), script generated (kicad-library-utils/schlib/autogen/connector/)</description>
      <docs>~</docs>
      <footprints>
        <fp>Connector*:*_2x??_*</fp>
      </footprints>
      <fields>
        <field name="Reference">J</field>
        <field name="Value">Conn_02x25_Odd_Even</field>
        <field name="Datasheet">~</field>
      </fields>
      <pins>
        <pin num="1" name="Pin_1" type="passive"/>
        <pin num="2" name="Pin_2" type="passive"/>
        <pin num="3" name="Pin_3" type="passive"/>
        <pin num="4" name="Pin_4" type="passive"/>
        <pin num="5" name="Pin_5" type="passive"/>
        <pin num="6" name="Pin_6" type="passive"/>
        <pin num="7" name="Pin_7" type="passive"/>
        <pin num="8" name="Pin_8" type="passive"/>
        <pin num="9" name="Pin_9" type="passive"/>
        <pin num="10" name="Pin_10" type="passive"/>
        <pin num="11" name="Pin_11" type="passive"/>
        <pin num="12" name="Pin_12" type="passive"/>
        <pin num="13" name="Pin_13" type="passive"/>
        <pin num="14" name="Pin_14" type="passive"/>
        <pin num="15" name="Pin_15" type="passive"/>
        <pin num="16" name="Pin_16" type="passive"/>
        <pin num="17" name="Pin_17" type="passive"/>
        <pin num="18" name="Pin_18" type="passive"/>
        <pin num="19" name="Pin_19" type="passive"/>
        <pin num="20" name="Pin_20" type="passive"/>
        <pin num="21" name="Pin_21" type="passive"/>
        <pin num="22" name="Pin_22" type="passive"/>
        <pin num="23" name="Pin_23" type="passive"/>
        <pin num="24" name="Pin_24" type="passive"/>
        <pin num="25" name="Pin_25" type="passive"/>
        <pin num="26" name="Pin_26" type="passive"/>
        <pin num="27" name="Pin_27" type="passive"/>
        <pin num="28" name="Pin_28" type="passive"/>
        <pin num="29" name="Pin_29" type="passive"/>
        <pin num="30" name="Pin_30" type="passive"/>
        <pin num="31" name="Pin_31" type="passive"/>
        <pin num="32" name="Pin_32" type="passive"/>
        <pin num="33" name="Pin_33" type="passive"/>
        <pin num="34" name="Pin_34" type="passive"/>
        <pin num="35" name="Pin_35" type="passive"/>
        <pin num="36" name="Pin_36" type="passive"/>
        <pin num="37" name="Pin_37" type="passive"/>
        <pin num="38" name="Pin_38" type="passive"/>
        <pin num="39" name="Pin_39" type="passive"/>
        <pin num="40" name="Pin_40" type="passive"/>
        <pin num="41" name="Pin_41" type="passive"/>
        <pin num="42" name="Pin_42" type="passive"/>
        <pin num="43" name="Pin_43" type="passive"/>
        <pin num="44" name="Pin_44" type="passive"/>
        <pin num="45" name="Pin_45" type="passive"/>
        <pin num="46" name="Pin_46" type="passive"/>
        <pin num="47" name="Pin_47" type="passive"/>
        <pin num="48" name="Pin_48" type="passive"/>
        <pin num="49" name="Pin_49" type="passive"/>
        <pin num="50" name="Pin_50" type="passive"/>
      </pins>
    </libpart>
    <libpart lib="Connector_Generic_MountingPin" part="Conn_01x16_MountingPin">
      <description>Generic connectable mounting pin connector, single row, 01x16, script generated (kicad-library-utils/schlib/autogen/connector/)</description>
      <docs>~</docs>
      <footprints>
        <fp>Connector*:*_1x??-1MP*</fp>
      </footprints>
      <fields>
        <field name="Reference">J</field>
        <field name="Value">Conn_01x16_MountingPin</field>
        <field name="Datasheet">~</field>
      </fields>
      <pins>
        <pin num="1" name="Pin_1" type="passive"/>
        <pin num="2" name="Pin_2" type="passive"/>
        <pin num="3" name="Pin_3" type="passive"/>
        <pin num="4" name="Pin_4" type="passive"/>
        <pin num="5" name="Pin_5" type="passive"/>
        <pin num="6" name="Pin_6" type="passive"/>
        <pin num="7" name="Pin_7" type="passive"/>
        <pin num="8" name="Pin_8" type="passive"/>
        <pin num="9" name="Pin_9" type="passive"/>
        <pin num="10" name="Pin_10" type="passive"/>
        <pin num="11" name="Pin_11" type="passive"/>
        <pin num="12" name="Pin_12" type="passive"/>
        <pin num="13" name="Pin_13" type="passive"/>
        <pin num="14" name="Pin_14" type="passive"/>
        <pin num="15" name="Pin_15" type="passive"/>
        <pin num="16" name="Pin_16" type="passive"/>
        <pin num="MP" name="MountPin" type="passive"/>
      </pins>
    </libpart>
    <libpart lib="Device" part="C_Small">
      <description>Unpolarized capacitor, small symbol</description>
      <docs>~</docs>
      <footprints>
        <fp>C_*</fp>
      </footprints>
      <fields>
        <field name="Reference">C</field>
        <field name="Value">C_Small</field>
        <field name="Datasheet">~</field>
      </fields>
      <pins>
        <pin num="1" name="" type="passive"/>
        <pin num="2" name="" type="passive"/>
      </pins>
    </libpart>
    <libpart lib="Device" part="L">
      <description>Inductor</description>
      <docs>~</docs>
      <footprints>
        <fp>Choke_*</fp>
        <fp>*Coil*</fp>
        <fp>Inductor_*</fp>
        <fp>L_*</fp>
      </footprints>
      <fields>
        <field name="Reference">L</field>
        <field name="Value">L</field>
        <field name="Datasheet">~</field>
      </fields>
      <pins>
        <pin num="1" name="1" type="passive"/>
        <pin num="2" name="2" type="passive"/>
      </pins>
    </libpart>
    <libpart lib="Device" part="Polyfuse">
      <description>Resettable fuse, polymeric positive temperature coefficient</description>
      <docs>~</docs>
      <footprints>
        <fp>*polyfuse*</fp>
        <fp>*PTC*</fp>
      </footprints>
      <fields>
        <field name="Reference">F</field>
        <field name="Value">Polyfuse</field>
        <field name="Datasheet">~</field>
      </fields>
      <pins>
        <pin num="1" name="" type="passive"/>
        <pin num="2" name="" type="passive"/>
      </pins>
    </libpart>
    <libpart lib="Device" part="R_Small">
      <description>Resistor, small symbol</description>
      <docs>~</docs>
      <footprints>
        <fp>R_*</fp>
      </footprints>
      <fields>
        <field name="Reference">R</field>
        <field name="Value">R_Small</field>
        <field name="Datasheet">~</field>
      </fields>
      <pins>
        <pin num="1" name="" type="passive"/>
        <pin num="2" name="" type="passive"/>
      </pins>
    </libpart>
    <libpart lib="Interface_CAN_LIN" part="ISO1044UB">
      <description>Isolated CAN Transceiver, SOP-8</description>
      <docs>http://www.ti.com/lit/ds/symlink/iso1050.pdf</docs>
      <footprints>
        <fp>SOP*6.62x9.15mm*P2.54mm*</fp>
      </footprints>
      <fields>
        <field name="Reference">U</field>
        <field name="Value">ISO1044UB</field>
        <field name="Footprint">Package_SO:SOIC-8_3.9x4.9mm_P1.27mm</field>
        <field name="Datasheet">http://www.ti.com/lit/ds/symlink/iso1050.pdf</field>
      </fields>
      <pins>
        <pin num="1" name="VCC1" type="power_in"/>
        <pin num="2" name="RXD" type="output"/>
        <pin num="3" name="TXD" type="input"/>
        <pin num="4" name="GND1" type="power_in"/>
        <pin num="5" name="CANL" type="bidirectional"/>
        <pin num="6" name="CANH" type="bidirectional"/>
        <pin num="7" name="GND2" type="power_in"/>
        <pin num="8" name="VCC2" type="power_in"/>
      </pins>
    </libpart>
    <libpart lib="LMR51430" part="LMR51430">
      <docs>https://www.ti.com/lit/ds/symlink/lmr51430.pdf?ts=1684716438866&amp;ref_url=https%253A%252F%252Fwww.ti.com%252Fproduct%252FLMR51430</docs>
      <fields>
        <field name="Reference">U</field>
        <field name="Value">LMR51430</field>
        <field name="Footprint">Package_TO_SOT_SMD:SOT-23-6</field>
        <field name="Datasheet">https://www.ti.com/lit/ds/symlink/lmr51430.pdf?ts=1684716438866&amp;ref_url=https%253A%252F%252Fwww.ti.com%252Fproduct%252FLMR51430</field>
      </fields>
      <pins>
        <pin num="1" name="GND" type="power_in"/>
        <pin num="2" name="SW" type="output"/>
        <pin num="3" name="VIN" type="power_in"/>
        <pin num="4" name="FB" type="input"/>
        <pin num="5" name="~{SHDN}" type="input"/>
        <pin num="6" name="CB" type="input"/>
      </pins>
    </libpart>
    <libpart lib="Mechanical" part="MountingHole_Pad">
      <description>Mounting Hole with connection</description>
      <docs>~</docs>
      <footprints>
        <fp>MountingHole*Pad*</fp>
      </footprints>
      <fields>
        <field name="Reference">H</field>
        <field name="Value">MountingHole_Pad</field>
        <field name="Datasheet">~</field>
      </fields>
      <pins>
        <pin num="1" name="1" type="input"/>
      </pins>
    </libpart>
  </libparts>
  <libraries>
    <library logical="Connector">
      <uri>C:\Program Files\KiCad\6.0\share\kicad\symbols\/Connector.kicad_sym</uri>
    </library>
    <library logical="Connector_Generic">
      <uri>C:\Program Files\KiCad\6.0\share\kicad\symbols\/Connector_Generic.kicad_sym</uri>
    </library>
    <library logical="Connector_Generic_MountingPin">
      <uri>C:\Program Files\KiCad\6.0\share\kicad\symbols\/Connector_Generic_MountingPin.kicad_sym</uri>
    </library>
    <library logical="Device">
      <uri>C:\Program Files\KiCad\6.0\share\kicad\symbols\/Device.kicad_sym</uri>
    </library>
    <library logical="Interface_CAN_LIN">
      <uri>C:/Users/penta/Documents/BikeRadar/RFB/library/Interface_CAN_LIN.kicad_sym</uri>
    </library>
    <library logical="LMR51430">
      <uri>C:/Users/penta/Documents/BikeRadar/RFB/library/LMR51430.kicad_sym</uri>
    </library>
    <library logical="Mechanical">
      <uri>C:\Program Files\KiCad\6.0\share\kicad\symbols\/Mechanical.kicad_sym</uri>
    </library>
  </libraries>
  <nets>
    <net code="1" name="+2V5">
      <node ref="C14" pin="2" pintype="passive"/>
      <node ref="J1" pin="3" pinfunction="Pin_3" pintype="passive"/>
      <node ref="J1" pin="4" pinfunction="Pin_4" pintype="passive"/>
      <node ref="J2" pin="16" pinfunction="Pin_16" pintype="passive"/>
    </net>
    <net code="2" name="+3V3">
      <node ref="C8" pin="2" pintype="passive"/>
      <node ref="J3" pin="11" pinfunction="Pin_11" pintype="passive"/>
      <node ref="J3" pin="12" pinfunction="Pin_12" pintype="passive"/>
      <node ref="J5" pin="1" pinfunction="Pin_1" pintype="passive"/>
      <node ref="U3" pin="1" pinfunction="VCC1" pintype="power_in"/>
    </net>
    <net code="3" name="+3V8">
      <node ref="C10" pin="2" pintype="passive"/>
      <node ref="C12" pin="2" pintype="passive"/>
      <node ref="J7" pin="3" pinfunction="Pin_3" pintype="passive"/>
      <node ref="L2" pin="2" pinfunction="2" pintype="passive"/>
      <node ref="R3" pin="1" pintype="passive"/>
    </net>
    <net code="4" name="+5V">
      <node ref="C1" pin="1" pintype="passive"/>
      <node ref="C11" pin="2" pintype="passive"/>
      <node ref="C13" pin="1" pintype="passive"/>
      <node ref="C9" pin="2" pintype="passive"/>
      <node ref="F1" pin="1" pintype="passive"/>
      <node ref="J1" pin="49" pinfunction="Pin_49" pintype="passive"/>
      <node ref="J1" pin="50" pinfunction="Pin_50" pintype="passive"/>
      <node ref="L1" pin="2" pinfunction="2" pintype="passive"/>
      <node ref="R1" pin="1" pintype="passive"/>
      <node ref="U3" pin="8" pinfunction="VCC2" pintype="power_in"/>
    </net>
    <net code="5" name="+6V">
      <node ref="C16" pin="2" pintype="passive"/>
      <node ref="C17" pin="2" pintype="passive"/>
      <node ref="J7" pin="1" pinfunction="Pin_1" pintype="passive"/>
      <node ref="L3" pin="2" pinfunction="2" pintype="passive"/>
      <node ref="R5" pin="1" pintype="passive"/>
    </net>
    <net code="6" name="+12V">
      <node ref="C2" pin="2" pintype="passive"/>
      <node ref="C3" pin="2" pintype="passive"/>
      <node ref="C4" pin="2" pintype="passive"/>
      <node ref="C5" pin="2" pintype="passive"/>
      <node ref="J4" pin="1" pinfunction="Pin_1" pintype="passive"/>
      <node ref="U1" pin="3" pinfunction="VIN" pintype="power_in"/>
      <node ref="U1" pin="5" pinfunction="~{SHDN}" pintype="input"/>
      <node ref="U2" pin="3" pinfunction="VIN" pintype="power_in"/>
      <node ref="U2" pin="5" pinfunction="~{SHDN}" pintype="input"/>
      <node ref="U4" pin="3" pinfunction="VIN" pintype="power_in"/>
      <node ref="U4" pin="5" pinfunction="~{SHDN}" pintype="input"/>
    </net>
    <net code="7" name="/CAN_R">
      <node ref="J3" pin="3" pinfunction="Pin_3" pintype="passive"/>
      <node ref="U3" pin="2" pinfunction="RXD" pintype="output"/>
    </net>
    <net code="8" name="/CAN_T">
      <node ref="J3" pin="4" pinfunction="Pin_4" pintype="passive"/>
      <node ref="U3" pin="3" pinfunction="TXD" pintype="input"/>
    </net>
    <net code="9" name="/DA0N">
      <node ref="J1" pin="20" pinfunction="Pin_20" pintype="passive"/>
      <node ref="J2" pin="3" pinfunction="Pin_3" pintype="passive"/>
    </net>
    <net code="10" name="/DA0P">
      <node ref="J1" pin="19" pinfunction="Pin_19" pintype="passive"/>
      <node ref="J2" pin="4" pinfunction="Pin_4" pintype="passive"/>
    </net>
    <net code="11" name="/DA1N">
      <node ref="J1" pin="18" pinfunction="Pin_18" pintype="passive"/>
      <node ref="J2" pin="5" pinfunction="Pin_5" pintype="passive"/>
    </net>
    <net code="12" name="/DA1P">
      <node ref="J1" pin="17" pinfunction="Pin_17" pintype="passive"/>
      <node ref="J2" pin="6" pinfunction="Pin_6" pintype="passive"/>
    </net>
    <net code="13" name="/DB0N">
      <node ref="J1" pin="11" pinfunction="Pin_11" pintype="passive"/>
      <node ref="J2" pin="11" pinfunction="Pin_11" pintype="passive"/>
    </net>
    <net code="14" name="/DB0P">
      <node ref="J1" pin="12" pinfunction="Pin_12" pintype="passive"/>
      <node ref="J2" pin="12" pinfunction="Pin_12" pintype="passive"/>
    </net>
    <net code="15" name="/DB1N">
      <node ref="J1" pin="9" pinfunction="Pin_9" pintype="passive"/>
      <node ref="J2" pin="13" pinfunction="Pin_13" pintype="passive"/>
    </net>
    <net code="16" name="/DB1P">
      <node ref="J1" pin="10" pinfunction="Pin_10" pintype="passive"/>
      <node ref="J2" pin="14" pinfunction="Pin_14" pintype="passive"/>
    </net>
    <net code="17" name="/DCLKN">
      <node ref="J1" pin="16" pinfunction="Pin_16" pintype="passive"/>
      <node ref="J2" pin="7" pinfunction="Pin_7" pintype="passive"/>
    </net>
    <net code="18" name="/DCLKP">
      <node ref="J1" pin="15" pinfunction="Pin_15" pintype="passive"/>
      <node ref="J2" pin="8" pinfunction="Pin_8" pintype="passive"/>
    </net>
    <net code="19" name="/F19">
      <node ref="J3" pin="1" pinfunction="Pin_1" pintype="passive"/>
    </net>
    <net code="20" name="/F20">
      <node ref="J3" pin="2" pinfunction="Pin_2" pintype="passive"/>
    </net>
    <net code="21" name="/FCLKN">
      <node ref="J1" pin="13" pinfunction="Pin_13" pintype="passive"/>
      <node ref="J2" pin="9" pinfunction="Pin_9" pintype="passive"/>
    </net>
    <net code="22" name="/FCLKP">
      <node ref="J1" pin="14" pinfunction="Pin_14" pintype="passive"/>
      <node ref="J2" pin="10" pinfunction="Pin_10" pintype="passive"/>
    </net>
    <net code="23" name="/H18">
      <node ref="J3" pin="5" pinfunction="Pin_5" pintype="passive"/>
    </net>
    <net code="24" name="/H20">
      <node ref="J3" pin="6" pinfunction="Pin_6" pintype="passive"/>
    </net>
    <net code="25" name="/J19">
      <node ref="J3" pin="7" pinfunction="Pin_7" pintype="passive"/>
    </net>
    <net code="26" name="/J20">
      <node ref="J3" pin="8" pinfunction="Pin_8" pintype="passive"/>
    </net>
    <net code="27" name="/N20">
      <node ref="J1" pin="6" pinfunction="Pin_6" pintype="passive"/>
    </net>
    <net code="28" name="/P14">
      <node ref="J1" pin="39" pinfunction="Pin_39" pintype="passive"/>
    </net>
    <net code="29" name="/P20">
      <node ref="J1" pin="5" pinfunction="Pin_5" pintype="passive"/>
    </net>
    <net code="30" name="/R19">
      <node ref="J1" pin="8" pinfunction="Pin_8" pintype="passive"/>
      <node ref="J2" pin="1" pinfunction="Pin_1" pintype="passive"/>
    </net>
    <net code="31" name="/T10">
      <node ref="J1" pin="45" pinfunction="Pin_45" pintype="passive"/>
    </net>
    <net code="32" name="/T11">
      <node ref="J1" pin="46" pinfunction="Pin_46" pintype="passive"/>
    </net>
    <net code="33" name="/T12">
      <node ref="J1" pin="43" pinfunction="Pin_43" pintype="passive"/>
    </net>
    <net code="34" name="/T14">
      <node ref="J1" pin="37" pinfunction="Pin_37" pintype="passive"/>
    </net>
    <net code="35" name="/T15">
      <node ref="J1" pin="38" pinfunction="Pin_38" pintype="passive"/>
    </net>
    <net code="36" name="/T19">
      <node ref="J1" pin="7" pinfunction="Pin_7" pintype="passive"/>
    </net>
    <net code="37" name="/U12">
      <node ref="J1" pin="44" pinfunction="Pin_44" pintype="passive"/>
    </net>
    <net code="38" name="/U14">
      <node ref="J1" pin="40" pinfunction="Pin_40" pintype="passive"/>
    </net>
    <net code="39" name="/U18">
      <node ref="J1" pin="21" pinfunction="Pin_21" pintype="passive"/>
    </net>
    <net code="40" name="/U19">
      <node ref="J1" pin="22" pinfunction="Pin_22" pintype="passive"/>
    </net>
    <net code="41" name="/V12">
      <node ref="J1" pin="41" pinfunction="Pin_41" pintype="passive"/>
    </net>
    <net code="42" name="/V15">
      <node ref="J1" pin="29" pinfunction="Pin_29" pintype="passive"/>
    </net>
    <net code="43" name="/V16">
      <node ref="J1" pin="27" pinfunction="Pin_27" pintype="passive"/>
    </net>
    <net code="44" name="/V17">
      <node ref="J1" pin="25" pinfunction="Pin_25" pintype="passive"/>
    </net>
    <net code="45" name="/V18">
      <node ref="J1" pin="26" pinfunction="Pin_26" pintype="passive"/>
    </net>
    <net code="46" name="/W13">
      <node ref="J1" pin="42" pinfunction="Pin_42" pintype="passive"/>
    </net>
    <net code="47" name="/W14">
      <node ref="J1" pin="35" pinfunction="Pin_35" pintype="passive"/>
    </net>
    <net code="48" name="/W15">
      <node ref="J1" pin="30" pinfunction="Pin_30" pintype="passive"/>
    </net>
    <net code="49" name="/W16">
      <node ref="J1" pin="28" pinfunction="Pin_28" pintype="passive"/>
    </net>
    <net code="50" name="/W18">
      <node ref="J1" pin="23" pinfunction="Pin_23" pintype="passive"/>
    </net>
    <net code="51" name="/W19">
      <node ref="J1" pin="24" pinfunction="Pin_24" pintype="passive"/>
    </net>
    <net code="52" name="/Y14">
      <node ref="J1" pin="36" pinfunction="Pin_36" pintype="passive"/>
    </net>
    <net code="53" name="/Y16">
      <node ref="J1" pin="33" pinfunction="Pin_33" pintype="passive"/>
    </net>
    <net code="54" name="/Y17">
      <node ref="J1" pin="34" pinfunction="Pin_34" pintype="passive"/>
    </net>
    <net code="55" name="/Y18">
      <node ref="J1" pin="31" pinfunction="Pin_31" pintype="passive"/>
    </net>
    <net code="56" name="/Y19">
      <node ref="J1" pin="32" pinfunction="Pin_32" pintype="passive"/>
    </net>
    <net code="57" name="GND">
      <node ref="C1" pin="2" pintype="passive"/>
      <node ref="C10" pin="1" pintype="passive"/>
      <node ref="C11" pin="1" pintype="passive"/>
      <node ref="C12" pin="1" pintype="passive"/>
      <node ref="C13" pin="2" pintype="passive"/>
      <node ref="C14" pin="1" pintype="passive"/>
      <node ref="C16" pin="1" pintype="passive"/>
      <node ref="C17" pin="1" pintype="passive"/>
      <node ref="C2" pin="1" pintype="passive"/>
      <node ref="C3" pin="1" pintype="passive"/>
      <node ref="C4" pin="1" pintype="passive"/>
      <node ref="C5" pin="1" pintype="passive"/>
      <node ref="C8" pin="1" pintype="passive"/>
      <node ref="C9" pin="1" pintype="passive"/>
      <node ref="H1" pin="1" pinfunction="1" pintype="input"/>
      <node ref="H2" pin="1" pinfunction="1" pintype="input"/>
      <node ref="J1" pin="1" pinfunction="Pin_1" pintype="passive"/>
      <node ref="J1" pin="2" pinfunction="Pin_2" pintype="passive"/>
      <node ref="J1" pin="47" pinfunction="Pin_47" pintype="passive"/>
      <node ref="J1" pin="48" pinfunction="Pin_48" pintype="passive"/>
      <node ref="J2" pin="15" pinfunction="Pin_15" pintype="passive"/>
      <node ref="J2" pin="2" pinfunction="Pin_2" pintype="passive"/>
      <node ref="J2" pin="MP" pinfunction="MountPin" pintype="passive"/>
      <node ref="J3" pin="10" pinfunction="Pin_10" pintype="passive"/>
      <node ref="J3" pin="9" pinfunction="Pin_9" pintype="passive"/>
      <node ref="J4" pin="2" pinfunction="Pin_2" pintype="passive"/>
      <node ref="J5" pin="2" pinfunction="Pin_2" pintype="passive"/>
      <node ref="J6" pin="2" pinfunction="Pin_2" pintype="passive"/>
      <node ref="J7" pin="2" pinfunction="Pin_2" pintype="passive"/>
      <node ref="R2" pin="2" pintype="passive"/>
      <node ref="R4" pin="2" pintype="passive"/>
      <node ref="R6" pin="2" pintype="passive"/>
      <node ref="U1" pin="1" pinfunction="GND" pintype="power_in"/>
      <node ref="U2" pin="1" pinfunction="GND" pintype="power_in"/>
      <node ref="U3" pin="4" pinfunction="GND1" pintype="power_in"/>
      <node ref="U3" pin="7" pinfunction="GND2" pintype="power_in"/>
      <node ref="U4" pin="1" pinfunction="GND" pintype="power_in"/>
    </net>
    <net code="58" name="Net-(C6-Pad1)">
      <node ref="C6" pin="1" pintype="passive"/>
      <node ref="L1" pin="1" pinfunction="1" pintype="passive"/>
      <node ref="U1" pin="2" pinfunction="SW" pintype="output"/>
    </net>
    <net code="59" name="Net-(C6-Pad2)">
      <node ref="C6" pin="2" pintype="passive"/>
      <node ref="U1" pin="6" pinfunction="CB" pintype="input"/>
    </net>
    <net code="60" name="Net-(C7-Pad1)">
      <node ref="C7" pin="1" pintype="passive"/>
      <node ref="L2" pin="1" pinfunction="1" pintype="passive"/>
      <node ref="U2" pin="2" pinfunction="SW" pintype="output"/>
    </net>
    <net code="61" name="Net-(C7-Pad2)">
      <node ref="C7" pin="2" pintype="passive"/>
      <node ref="U2" pin="6" pinfunction="CB" pintype="input"/>
    </net>
    <net code="62" name="Net-(C15-Pad1)">
      <node ref="C15" pin="1" pintype="passive"/>
      <node ref="L3" pin="1" pinfunction="1" pintype="passive"/>
      <node ref="U4" pin="2" pinfunction="SW" pintype="output"/>
    </net>
    <net code="63" name="Net-(C15-Pad2)">
      <node ref="C15" pin="2" pintype="passive"/>
      <node ref="U4" pin="6" pinfunction="CB" pintype="input"/>
    </net>
    <net code="64" name="Net-(F1-Pad2)">
      <node ref="F1" pin="2" pintype="passive"/>
      <node ref="J6" pin="1" pinfunction="Pin_1" pintype="passive"/>
    </net>
    <net code="65" name="Net-(J6-Pad3)">
      <node ref="J6" pin="3" pinfunction="Pin_3" pintype="passive"/>
      <node ref="U3" pin="6" pinfunction="CANH" pintype="bidirectional"/>
    </net>
    <net code="66" name="Net-(J6-Pad4)">
      <node ref="J6" pin="4" pinfunction="Pin_4" pintype="passive"/>
      <node ref="U3" pin="5" pinfunction="CANL" pintype="bidirectional"/>
    </net>
    <net code="67" name="Net-(R1-Pad2)">
      <node ref="R1" pin="2" pintype="passive"/>
      <node ref="R2" pin="1" pintype="passive"/>
      <node ref="U1" pin="4" pinfunction="FB" pintype="input"/>
    </net>
    <net code="68" name="Net-(R3-Pad2)">
      <node ref="R3" pin="2" pintype="passive"/>
      <node ref="R4" pin="1" pintype="passive"/>
      <node ref="U2" pin="4" pinfunction="FB" pintype="input"/>
    </net>
    <net code="69" name="Net-(R5-Pad2)">
      <node ref="R5" pin="2" pintype="passive"/>
      <node ref="R6" pin="1" pintype="passive"/>
      <node ref="U4" pin="4" pinfunction="FB" pintype="input"/>
    </net>
  </nets>
</export>
